MANIFEST.in
README.rst
setup.py
bin/ploader
ploader/__init__.py
ploader/commands.py
ploader/dlc_handler.py
ploader/download_handler.py
ploader/link_loader.py
ploader/rar_handler.py
ploader/server.py
ploader/utils.py
ploader.egg-info/PKG-INFO
ploader.egg-info/SOURCES.txt
ploader.egg-info/dependency_links.txt
ploader.egg-info/not-zip-safe
ploader.egg-info/requires.txt
ploader.egg-info/top_level.txt
ploader/tests/__init__.py
ploader/tests/environment_handler.py
ploader/tests/test_config_handler.py
ploader/tests/test_download_handler.py
ploader/tests/test_link_loader.py
ploader/tests/test_server_commands.py
ploader/tests/test_utils.py