Metadata-Version: 1.0
Name: ploader
Version: 0.5.0
Summary: A pure cli-based download manager
Home-page: https://github.com/kpj/PLoader
Author: kpj
Author-email: kpjkpjkpjkpjkpjkpj@gmail.com
License: MIT
Platform: UNKNOWN
